mtprof/__init__.py
mtprof/__main__.py
mtprof/tests/__init__.py
mtprof/tests/__main__.py
mtprof/tests/test_mtprof.py
mtprof-0.0.3.dist-info/DESCRIPTION.rst
mtprof-0.0.3.dist-info/METADATA
mtprof-0.0.3.dist-info/RECORD
mtprof-0.0.3.dist-info/WHEEL
mtprof-0.0.3.dist-info/metadata.json
mtprof-0.0.3.dist-info/top_level.txt
