Metadata-Version: 2.0
Name: mtprof
Version: 0.0.3
Summary: Thread-aware profiler
Home-page: https://github.com/dask/mtprof
Author: Antoine Pitrou
Author-email: antoine@python.org
License: BSD
Platform: UNKNOWN
Classifier: Development Status :: 2 - Pre-Alpha
Classifier: Intended Audience :: Developers
Classifier: License :: OSI Approved :: BSD License
Classifier: Operating System :: POSIX
Classifier: Programming Language :: Python :: 3 :: Only
Classifier: Programming Language :: Python :: 3.5
Classifier: Programming Language :: Python :: 3.6
Classifier: Topic :: Software Development
Requires-Python: >=3
